sentry_conventions/__init__.py
sentry_conventions/attributes.py
sentry_conventions/py.typed
sentry_conventions-0.3.0.dist-info/METADATA
sentry_conventions-0.3.0.dist-info/WHEEL
sentry_conventions-0.3.0.dist-info/top_level.txt
sentry_conventions-0.3.0.dist-info/RECORD
