Metadata-Version: 2.1
Name: sentry-conventions
Version: 0.3.0
Summary: Sentry Semantic Conventions
License: MIT
Project-URL: Homepage, https://sentry.io
Project-URL: Repository, https://github.com/getsentry/sentry-conventions.git
Project-URL: Issues, https://github.com/getsentry/sentry-conventions/issues
Requires-Python: >=3.8
